{
  "indexes": [
    {
      "collectionGroup": "events",
      "queryScope": "COLLECTION",
      "fields": [
        {
          "fieldPath": "hidden",
          "order": "ASCENDING"
        },
        {
          "fieldPath": "time",
          "order": "ASCENDING"
        }
      ]
    },
    {
      "collectionGroup": "events",
      "queryScope": "COLLECTION",
      "fields": [
        {
          "fieldPath": "hidden",
          "order": "ASCENDING"
        },
        {
          "fieldPath": "region",
          "order": "ASCENDING"
        },
        {
          "fieldPath": "time",
          "order": "ASCENDING"
        }
      ]
    },
    {
      "collectionGroup": "events",
      "queryScope": "COLLECTION",
      "fields": [
        {
          "fieldPath": "hidden",
          "order": "ASCENDING"
        },
        {
          "fieldPath": "featured",
          "order": "ASCENDING"
        },
        {
          "fieldPath": "time",
          "order": "ASCENDING"
        }
      ]
    },
    {
      "collectionGroup": "links",
      "queryScope": "COLLECTION",
      "fields": [
        {
          "fieldPath": "parentId",
          "order": "ASCENDING"
        },
        {
          "fieldPath": "sortOrder",
          "order": "ASCENDING"
        }
      ]
    },
    {
      "collectionGroup": "events",
      "queryScope": "COLLECTION",
      "fields": [
        {
          "fieldPath": "organizerId",
          "order": "ASCENDING"
        },
        {
          "fieldPath": "time",
          "order": "ASCENDING"
        }
      ]
    }
  ],
  "fieldOverrides": []
}
